_pyoslog.cpython-310-darwin.so
pyoslog/__init__.py
pyoslog/__version__.py
pyoslog/_pyoslog.c
pyoslog/compatibility.py
pyoslog/core.py
pyoslog/handler.py
pyoslog-1.2.0.dist-info/licenses/LICENSE
pyoslog-1.2.0.dist-info/METADATA
pyoslog-1.2.0.dist-info/WHEEL
pyoslog-1.2.0.dist-info/top_level.txt
pyoslog-1.2.0.dist-info/RECORD
