Metadata-Version: 2.4
Name: pyoslog
Version: 1.2.0
Summary: Send messages to the macOS unified logging system (os_log)
Home-page: https://github.com/simonrob/pyoslog
Author: Simon Robinson
Author-email: simon@robinson.ac
License: Apache-2.0
Project-URL: Documentation, https://pyoslog.readthedocs.io/
Project-URL: Bug Tracker, https://github.com/simonrob/pyoslog/issues
Project-URL: Source Code, https://github.com/simonrob/pyoslog
Platform: darwin
Classifier: Operating System :: MacOS
Classifier: Programming Language :: Python
Classifier: Programming Language :: C
Classifier: Topic :: Software Development
Classifier: Topic :: System :: Logging
Classifier: Typing :: Typed
Classifier: Intended Audience :: Developers
Classifier: Development Status :: 5 - Production/Stable
License-File: LICENSE
Dynamic: author
Dynamic: author-email
Dynamic: classifier
Dynamic: description
Dynamic: description-content-type
Dynamic: home-page
Dynamic: license
Dynamic: license-file
Dynamic: platform
Dynamic: project-url
Dynamic: summary
